erezutils.py
erezutils-2.2.0.dist-info/LICENSE
erezutils-2.2.0.dist-info/METADATA
erezutils-2.2.0.dist-info/WHEEL
erezutils-2.2.0.dist-info/top_level.txt
erezutils-2.2.0.dist-info/RECORD
